coingate_interface/__init__.py
coingate_interface/coingate_interface.py
coingate_interface-1.0.1.dist-info/METADATA
coingate_interface-1.0.1.dist-info/WHEEL
coingate_interface-1.0.1.dist-info/top_level.txt
coingate_interface-1.0.1.dist-info/RECORD
